pysql/__init__.py
pysql/__version__.py
pysql/main.py
pysql/main_c.py
pysql/data/__init__.py
pysql/data/export.py
pysql/data/imports.py
pysql/data/info.py
pysql/packages/__init__.py
pysql/packages/auth.py
pysql/packages/ddl_commands.py
pysql/packages/dml_commands.py
pysql/utils/__init__.py
pysql/utils/exceptions.py
pysql/utils/update.py
pysql/utils/user.py
tests/__init__.py
tests/template.py
tests/data/__init__.py
tests/data/test_export.py
tests/data/test_imports.py
tests/packages/__init__.py
tests/packages/test_auth.py
tests/packages/test_ddl_commands.py
tests/packages/test_dml_commands.py
tests/utils/__init__.py
tests/utils/test_user.py
pysql_cli-1.1.2.dist-info/LICENSE
pysql_cli-1.1.2.dist-info/METADATA
pysql_cli-1.1.2.dist-info/WHEEL
pysql_cli-1.1.2.dist-info/entry_points.txt
pysql_cli-1.1.2.dist-info/top_level.txt
pysql_cli-1.1.2.dist-info/RECORD
