Metadata-Version: 2.1
Name: pysql-cli
Version: 1.1.2
Summary: CLI for making MySQL queries easier
Home-page: https://github.com/Devansh3712/PySQL
Author: Devansh Singh
Author-email: devanshamity@gmail.com
License: MIT
Platform: UNKNOWN
Classifier: Programming Language :: Python :: 3
Classifier: License :: OSI Approved :: MIT License
Classifier: Operating System :: OS Independent
License-File: LICENSE
Requires-Dist: mysql (==0.0.3)
Requires-Dist: mysql-connector (==2.2.9)
Requires-Dist: mysql-connector-python (==8.0.21)
Requires-Dist: tabulate (==0.8.7)
Requires-Dist: stdiomask (==0.0.6)
Requires-Dist: colorama (==0.4.4)
Requires-Dist: urllib3 (==1.26.3)
Requires-Dist: python-dotenv (==0.17.0)
